{
  "graph":{
    "layout_direction":0,
    "acyclic":true,
    "pipe_collision":false,
    "pipe_slicing":true,
    "pipe_style":1,
    "accept_connection_types":"{}",
    "reject_connection_types":"{}"
  },
  "nodes":{
    "0x16179a1e380":{
      "type_":"dynamic.StatusDynamicNode_\u6570\u636e\u96c6\u6210_CSV_\u8bfb\u53d6\u5668",
      "icon":null,
      "name":"CSV \u8bfb\u53d6\u5668",
      "color":[
        25,
        70,
        45,
        255
      ],
      "border_color":[
        74,
        84,
        85,
        255
      ],
      "text_color":[
        255,
        255,
        255,
        180
      ],
      "disabled":false,
      "selected":false,
      "visible":true,
      "width":160,
      "height":60,
      "pos":[
        55.797885139076925,
        183.48919920734912
      ],
      "layout_direction":0,
      "port_deletion_allowed":false,
      "subgraph_session":{}
    },
    "0x16179a377c0":{
      "type_":"dynamic.StatusDynamicNode_\u7b97\u6cd5_\u903b\u8f91\u56de\u5f52",
      "icon":null,
      "name":"\u903b\u8f91\u56de\u5f52",
      "color":[
        25,
        70,
        45,
        255
      ],
      "border_color":[
        74,
        84,
        85,
        255
      ],
      "text_color":[
        255,
        255,
        255,
        180
      ],
      "disabled":false,
      "selected":true,
      "visible":true,
      "width":253.0,
      "height":153.05,
      "pos":[
        366.97839841469823,
        138.42167659501777
      ],
      "layout_direction":0,
      "port_deletion_allowed":false,
      "subgraph_session":{},
      "custom":{
        "solver":"liblinear",
        "max_iter":"100",
        "test_size":"0.2"
      }
    }
  },
  "connections":[
    {
      "out":[
        "0x16179a1e380",
        "csv"
      ],
      "in":[
        "0x16179a377c0",
        "file"
      ]
    }
  ]
}